multistate_kernel/__init__.py
multistate_kernel/kernel.py
multistate_kernel/util.py
gp_multistate_kernel-0.0.11.dist-info/METADATA
gp_multistate_kernel-0.0.11.dist-info/WHEEL
gp_multistate_kernel-0.0.11.dist-info/top_level.txt
gp_multistate_kernel-0.0.11.dist-info/RECORD
